torchRDS/RDS.py
torchRDS/__init__.py
torchRDS-0.3.dist-info/LICENSE.txt
torchRDS-0.3.dist-info/METADATA
torchRDS-0.3.dist-info/WHEEL
torchRDS-0.3.dist-info/top_level.txt
torchRDS-0.3.dist-info/RECORD
