Metadata-Version: 2.1
Name: torchRDS
Version: 0.3
Summary: Reinforced Data Sampling for Model Diversification
Home-page: https://github.com/probeu/RDS
Author: Harry Nguyen
Author-email: harry.nguyen@outlook.com
License: MIT
Download-URL: https://github.com/probeu/RDS/archive/v_03.tar.gz
Keywords: Data-Sampling,Reinforcement-Learning,Machine-Learning
Platform: UNKNOWN
Classifier: Development Status :: 4 - Beta
Classifier: Intended Audience :: Developers
Classifier: Topic :: Software Development :: Build Tools
Classifier: License :: OSI Approved :: MIT License
Classifier: Programming Language :: Python :: 3
Requires-Dist: numpy
Requires-Dist: torch
Requires-Dist: scikit-learn
Requires-Dist: pandas
